saft/__init__.py
saft/saft.py
saft/test.py
saft/utils.py
saft/utils/__init__.py
saft/utils/utils.py
saft-1.2.0.dist-info/METADATA
saft-1.2.0.dist-info/WHEEL
saft-1.2.0.dist-info/top_level.txt
saft-1.2.0.dist-info/RECORD
