Metadata-Version: 2.1
Name: saft
Version: 1.2.0
Summary: SAFT: Self-Attention Factor-Tuning for Parameter-Efficient Fine-Tuning
Requires-Dist: torch
Requires-Dist: torchvision
Requires-Dist: timm
Requires-Dist: avalanche-lib
